kdecorators/__init__.py
kdecorators/decorators.py
kdecorators-0.1.dist-info/LICENSE
kdecorators-0.1.dist-info/METADATA
kdecorators-0.1.dist-info/WHEEL
kdecorators-0.1.dist-info/top_level.txt
kdecorators-0.1.dist-info/RECORD
